libvmd/__init__.py
libvmd/vmd.py
libvmd-0.0.3.dist-info/LICENSE
libvmd-0.0.3.dist-info/METADATA
libvmd-0.0.3.dist-info/WHEEL
libvmd-0.0.3.dist-info/top_level.txt
libvmd-0.0.3.dist-info/RECORD
