Metadata-Version: 2.1
Name: libvmd
Version: 0.0.3
Summary: LIBVMD: Python library for variational mode decomposition for both 1D and 2D
Home-page: https://github.com/hyoddubi1/libvmd
Author: Hyoseob Noh
Author-email: hyoddubi@naver.com
Classifier: Programming Language :: Python :: 3
Classifier: License :: OSI Approved :: MIT License
Classifier: Operating System :: OS Independent
License-File: LICENSE
Requires-Dist: numpy (>=1.20.0)
